{
  "formatVersion": 1,
  "database": {
    "version": 1,
    "identityHash": "0e43053e75062c3a6a6d40beecf00dbe",
    "entities": [
      {
        "tableName": "agentic_skills",
        "createSql": "CREATE TABLE IF NOT EXISTS `${TABLE_NAME}` (`id` INTEGER PRIMARY KEY AUTOINCREMENT NOT NULL, `name` TEXT NOT NULL, `emoji` TEXT NOT NULL, `actionType` TEXT NOT NULL, `uriTemplate` TEXT NOT NULL, `triggers` TEXT NOT NULL, `labelTemplate` TEXT NOT NULL, `enabled` INTEGER NOT NULL, `builtin` INTEGER NOT NULL, `sortOrder` INTEGER NOT NULL, `usageCount` INTEGER NOT NULL, `lastUsed` INTEGER NOT NULL)",
        "fields": [
          {
            "fieldPath": "id",
            "columnName": "id",
            "affinity": "INTEGER",
            "notNull": true
          },
          {
            "fieldPath": "name",
            "columnName": "name",
            "affinity": "TEXT",
            "notNull": true
          },
          {
            "fieldPath": "emoji",
            "columnName": "emoji",
            "affinity": "TEXT",
            "notNull": true
          },
          {
            "fieldPath": "actionType",
            "columnName": "actionType",
            "affinity": "TEXT",
            "notNull": true
          },
          {
            "fieldPath": "uriTemplate",
            "columnName": "uriTemplate",
            "affinity": "TEXT",
            "notNull": true
          },
          {
            "fieldPath": "triggers",
            "columnName": "triggers",
            "affinity": "TEXT",
            "notNull": true
          },
          {
            "fieldPath": "labelTemplate",
            "columnName": "labelTemplate",
            "affinity": "TEXT",
            "notNull": true
          },
          {
            "fieldPath": "enabled",
            "columnName": "enabled",
            "affinity": "INTEGER",
            "notNull": true
          },
          {
            "fieldPath": "builtin",
            "columnName": "builtin",
            "affinity": "INTEGER",
            "notNull": true
          },
          {
            "fieldPath": "sortOrder",
            "columnName": "sortOrder",
            "affinity": "INTEGER",
            "notNull": true
          },
          {
            "fieldPath": "usageCount",
            "columnName": "usageCount",
            "affinity": "INTEGER",
            "notNull": true
          },
          {
            "fieldPath": "lastUsed",
            "columnName": "lastUsed",
            "affinity": "INTEGER",
            "notNull": true
          }
        ],
        "primaryKey": {
          "autoGenerate": true,
          "columnNames": [
            "id"
          ]
        },
        "indices": [],
        "foreignKeys": []
      }
    ],
    "views": [],
    "setupQueries": [
      "CREATE TABLE IF NOT EXISTS room_master_table (id INTEGER PRIMARY KEY,identity_hash TEXT)",
      "INSERT OR REPLACE INTO room_master_table (id,identity_hash) VALUES(42, '0e43053e75062c3a6a6d40beecf00dbe')"
    ]
  }
}